menumaker/__init__.py
menumaker/constructor.py
menumaker-1.4.1.dist-info/DESCRIPTION.rst
menumaker-1.4.1.dist-info/METADATA
menumaker-1.4.1.dist-info/RECORD
menumaker-1.4.1.dist-info/WHEEL
menumaker-1.4.1.dist-info/metadata.json
menumaker-1.4.1.dist-info/top_level.txt
