Metadata-Version: 2.0
Name: menumaker
Version: 1.4.1
Summary: An easy solution for creating menus for TkInter applications in just a few lines.
Home-page: https://github.com/DeflatedPickle/MenuMaker
Author: DeflatedPickle
Author-email: DeflatedPickle@gmail.com
License: MIT
Keywords: menumaker,tkinter,GUI,menu
Platform: UNKNOWN
Classifier: Intended Audience :: Developers
Classifier: License :: OSI Approved :: MIT License
Classifier: Programming Language :: Python :: 2.6
Classifier: Programming Language :: Python :: 2.7
Classifier: Programming Language :: Python :: 3.0
Classifier: Programming Language :: Python :: 3.1
Classifier: Programming Language :: Python :: 3.2
Classifier: Programming Language :: Python :: 3.3
Classifier: Programming Language :: Python :: 3.4
Classifier: Programming Language :: Python :: 3.5
Classifier: Programming Language :: Python :: 3.6
